MANIFEST.in
README.md
README.txt
example_rules.ypac
pacbot.vim
rules.ypac
setup.py
MacPacbot/__init__.py
MacPacbot/pacbot.py
MacPacbot.egg-info/PKG-INFO
MacPacbot.egg-info/SOURCES.txt
MacPacbot.egg-info/dependency_links.txt
MacPacbot.egg-info/entry_points.txt
MacPacbot.egg-info/requires.txt
MacPacbot.egg-info/top_level.txt