Metadata-Version: 1.1
Name: MacPacbot
Version: 1.0.9
Summary: MacPacbot is a Python toolkit of PAC(auto proxy configuration) for Mac OS X
Home-page: http://dexteryy.github.com/MacPacbot
Author: dexteryy
Author-email: dexter.yy@gmail.com
License: UNKNOWN
Keywords: PAC,proxy,mac,GFW
Platform: UNKNOWN
Classifier: Programming Language :: Python
Classifier: Programming Language :: Python :: 3
Classifier: Development Status :: 4 - Beta
Classifier: Environment :: MacOS X
Classifier: Intended Audience :: Developers
Classifier: License :: OSI Approved :: MIT License
Classifier: Operating System :: MacOS :: MacOS X
Classifier: Topic :: System :: Systems Administration
